yatotem2scdl/TotemMetadataHandler.py
yatotem2scdl/__init__.py
yatotem2scdl/conversion.py
yatotem2scdl/data_structures.py
yatotem2scdl/exceptions.py
yatotem2scdl/main.py
yatotem2scdl/planDeCompte-vide.xml
yatotem2scdl/xsl/totem2xmlcsv.xsl
yatotem2scdl-0.1.5.dist-info/LICENSE
yatotem2scdl-0.1.5.dist-info/METADATA
yatotem2scdl-0.1.5.dist-info/WHEEL
yatotem2scdl-0.1.5.dist-info/entry_points.txt
yatotem2scdl-0.1.5.dist-info/top_level.txt
yatotem2scdl-0.1.5.dist-info/RECORD
