Metadata-Version: 2.2
Name: yatotem2scdl
Version: 0.1.5
Requires-Python: >=3.9
License-File: LICENSE
Requires-Dist: lxml
Provides-Extra: dev
Requires-Dist: build; extra == "dev"
Requires-Dist: black; extra == "dev"
Requires-Dist: mypy; extra == "dev"
Requires-Dist: twine; extra == "dev"
Provides-Extra: test
Requires-Dist: pytest; extra == "test"
Requires-Dist: pytest-watch; extra == "test"
Requires-Dist: csv-diff; extra == "test"
